AUTHORS
LICENSE
MANIFEST.in
README.md
setup.cfg
setup.py
dj_rest_auth/__init__.py
dj_rest_auth/__version__.py
dj_rest_auth/admin.py
dj_rest_auth/app_settings.py
dj_rest_auth/forms.py
dj_rest_auth/jwt_auth.py
dj_rest_auth/models.py
dj_rest_auth/serializers.py
dj_rest_auth/social_serializers.py
dj_rest_auth/urls.py
dj_rest_auth/utils.py
dj_rest_auth/views.py
dj_rest_auth.egg-info/PKG-INFO
dj_rest_auth.egg-info/SOURCES.txt
dj_rest_auth.egg-info/dependency_links.txt
dj_rest_auth.egg-info/not-zip-safe
dj_rest_auth.egg-info/requires.txt
dj_rest_auth.egg-info/top_level.txt
dj_rest_auth/__pycache__/__init__.cpython-38.pyc
dj_rest_auth/__pycache__/admin.cpython-38.pyc
dj_rest_auth/__pycache__/app_settings.cpython-38.pyc
dj_rest_auth/__pycache__/forms.cpython-38.pyc
dj_rest_auth/__pycache__/jwt_auth.cpython-38.pyc
dj_rest_auth/__pycache__/models.cpython-38.pyc
dj_rest_auth/__pycache__/serializers.cpython-38.pyc
dj_rest_auth/__pycache__/social_serializers.cpython-38.pyc
dj_rest_auth/__pycache__/urls.cpython-38.pyc
dj_rest_auth/__pycache__/utils.cpython-38.pyc
dj_rest_auth/__pycache__/views.cpython-38.pyc
dj_rest_auth/locale/ar/LC_MESSAGES/django.po
dj_rest_auth/locale/cs/LC_MESSAGES/.!63502!django.mo
dj_rest_auth/locale/cs/LC_MESSAGES/.!64462!django.mo
dj_rest_auth/locale/cs/LC_MESSAGES/.!64600!django.mo
dj_rest_auth/locale/cs/LC_MESSAGES/.!64760!django.mo
dj_rest_auth/locale/cs/LC_MESSAGES/.!65418!django.mo
dj_rest_auth/locale/cs/LC_MESSAGES/.!65616!django.mo
dj_rest_auth/locale/cs/LC_MESSAGES/.!65791!django.mo
dj_rest_auth/locale/cs/LC_MESSAGES/.!65995!django.mo
dj_rest_auth/locale/cs/LC_MESSAGES/.!69818!django.mo
dj_rest_auth/locale/cs/LC_MESSAGES/django.mo
dj_rest_auth/locale/cs/LC_MESSAGES/django.po
dj_rest_auth/locale/de/LC_MESSAGES/.!65618!django.mo
dj_rest_auth/locale/de/LC_MESSAGES/.!65793!django.mo
dj_rest_auth/locale/de/LC_MESSAGES/.!65997!django.mo
dj_rest_auth/locale/de/LC_MESSAGES/.!69820!django.mo
dj_rest_auth/locale/de/LC_MESSAGES/django.mo
dj_rest_auth/locale/de/LC_MESSAGES/django.po
dj_rest_auth/locale/es/LC_MESSAGES/.!65620!django.mo
dj_rest_auth/locale/es/LC_MESSAGES/.!65795!django.mo
dj_rest_auth/locale/es/LC_MESSAGES/.!65999!django.mo
