Metadata-Version: 2.1
Name: dj-rest-auth
Version: 2.2.8
Summary: Authentication and Registration in Django Rest Framework
Home-page: http://github.com/iMerica/dj-rest-auth
Author: iMerica
Author-email: imichael@pm.me
License: MIT
Keywords: django rest auth registration rest-framework django-registration api
Platform: UNKNOWN
Classifier: Framework :: Django
Classifier: Intended Audience :: Developers
Classifier: Intended Audience :: System Administrators
Classifier: Operating System :: OS Independent
Classifier: Topic :: Software Development
Requires-Python: >=3.5
Provides-Extra: with_social
